outlify/__init__.py
outlify/_ansi.py
outlify/_utils.py
outlify/decorators.py
outlify/list.py
outlify/panel.py
outlify/style.py
outlify-0.10.0.dist-info/METADATA
outlify-0.10.0.dist-info/WHEEL
outlify-0.10.0.dist-info/licenses/LICENSE
outlify-0.10.0.dist-info/RECORD
