Metadata-Version: 2.4
Name: outlify
Version: 0.10.0
Summary: Structured cli output — beautifully, simply, and dependency-free
Project-URL: Homepage, https://k1shk1n.github.io/outlify
Project-URL: Source, https://github.com/k1shk1n/outlify
Project-URL: Bug Tracker, https://github.com/k1shk1n/outlify/issues
Project-URL: Documentation, https://k1shk1n.github.io/outlify
Author-email: Vladislav Kishkin <vladislav.kishkin01@gmail.com>
Maintainer-email: Vladislav Kishkin <vladislav.kishkin01@gmail.com>
License-Expression: MIT
License-File: LICENSE
Keywords: cli,developer-tools,logs,outlify,output,utilities
Classifier: Environment :: Console
Classifier: Intended Audience :: Developers
Classifier: License :: OSI Approved :: MIT License
Classifier: Operating System :: OS Independent
Classifier: Programming Language :: Python :: 3
Classifier: Programming Language :: Python :: 3.10
Classifier: Programming Language :: Python :: 3.11
Classifier: Programming Language :: Python :: 3.12
Classifier: Programming Language :: Python :: 3.13
Classifier: Topic :: Software Development :: Libraries
Classifier: Topic :: Utilities
Requires-Python: >=3.10
Provides-Extra: dev
Requires-Dist: pytest-cov==6.1.1; extra == 'dev'
Requires-Dist: pytest==8.3.5; extra == 'dev'
Requires-Dist: ruff==0.11.4; extra == 'dev'
Provides-Extra: docs
Requires-Dist: mike==2.1.3; extra == 'docs'
Requires-Dist: mkdocs-material==9.6.11; extra == 'docs'
